voicennl.py
voicennl-1.0.0.dist-info/WHEEL
voicennl-1.0.0.dist-info/METADATA
voicennl-1.0.0.dist-info/RECORD
