Metadata-Version: 2.1
Name: voicennl
Version: 1.0.0
Summary: ConventorizationShell("testvoice.txt").langDE()
Author: adamsonScripts
Requires-Python: >=3.6,<4.0
Classifier: Programming Language :: Python :: 3
Classifier: Programming Language :: Python :: 3.10
Classifier: Programming Language :: Python :: 3.6
Classifier: Programming Language :: Python :: 3.7
Classifier: Programming Language :: Python :: 3.8
Classifier: Programming Language :: Python :: 3.9
